Metadata-Version: 2.4
Name: gptables
Version: 2.0.0
Summary: Simplifying good practice in statistical tables.
Author-email: Analysis Standards and Pipelines <ASAP@ons.gov.uk>
Maintainer-email: Analysis Standards and Pipelines <ASAP@ons.gov.uk>
License: MIT License
Project-URL: Homepage, https://github.com/best-practice-and-impact/gptables
Project-URL: Documentation, https://gptables.readthedocs.io/en/latest/
Keywords: reproducible,tables,excel,xlsxwriter,reproducible-analytical-pipelines
Classifier: Programming Language :: Python :: 3
Classifier: Operating System :: OS Independent
Requires-Python: >=3.9
License-File: LICENSE
Requires-Dist: pandas>=2.3.2
Requires-Dist: xlrd>=2.0.2
Requires-Dist: XlsxWriter>=3.2.9
Requires-Dist: pyyaml>=6.0.2
Provides-Extra: docs
Requires-Dist: mkdocs; extra == "docs"
Requires-Dist: mkdocs-material; extra == "docs"
Requires-Dist: mkdocs-git-revision-date-localized-plugin; extra == "docs"
Requires-Dist: mkdocs-print-site-plugin; extra == "docs"
Requires-Dist: mkdocstrings-python; extra == "docs"
Requires-Dist: mkdocs-material; extra == "docs"
Requires-Dist: pymdown-extensions; extra == "docs"
Provides-Extra: dev
Requires-Dist: coverage; extra == "dev"
Requires-Dist: pytest>=8.4.2; extra == "dev"
Requires-Dist: pytest-cov; extra == "dev"
Requires-Dist: pre-commit; extra == "dev"
Requires-Dist: importlib_resources; extra == "dev"
Requires-Dist: pytest-regressions; extra == "dev"
Dynamic: license-file
